{
  "kind": "collectionType",
  "collectionName": "posts",
  "info": {
    "singularName": "post",
    "pluralName": "posts",
    "displayName": "post"
  },
  "options": {
    "draftAndPublish": true
  },
  "pluginOptions": {},
  "attributes": {
    "title": {
      "type": "string"
    },
    "content": {
      "type": "text"
    },
    "image": {
      "allowedTypes": [
        "images",
        "files",
        "videos"
      ],
      "type": "media",
      "multiple": true
    },
    "comments": {
      "type": "relation",
      "relation": "oneToMany",
      "target": "api::comment.comment",
      "mappedBy": "post"
    }
  }
}
